LICENSE
MANIFEST.in
README.rst
requirements.txt
requirements_dev.txt
setup.cfg
setup.py
docs/Makefile
docs/conf.py
docs/getting-started.rst
docs/index.rst
docs/make.bat
docs/source/example.rst
docs/source/karld.record_reader.rst
docs/source/karld.rst
docs/source/karld.tests.rst
karld/__init__.py
karld/_meta.py
karld/conversion_operators.py
karld/io.py
karld/iter_utils.py
karld/loadump.py
karld/merger.py
karld/path.py
karld/run_together.py
karld/tap.py
karld/unicode_io.py
karld.egg-info/PKG-INFO
karld.egg-info/SOURCES.txt
karld.egg-info/dependency_links.txt
karld.egg-info/requires.txt
karld.egg-info/top_level.txt
karld/record_reader/__init__.py
karld/record_reader/app_engine.py
karld/tests/__init__.py
karld/tests/test_conversion_operators.py
karld/tests/test_loadump.py
karld/tests/test_path.py
karld/tests/test_record_reader.py
karld/tests/test_run_together.py
karld/tests/test_tap.py
karld/tests/test_unicode_io.py