Metadata-Version: 1.1
Name: karld
Version: 0.3.1
Summary: Doing some data things in a memory efficient manner
Home-page: https://github.com/johnwlockwood/karl_data
Author: John W Lockwood IV
Author-email: john@tackletronics.com
License:                                  Apache License
